fisher_scoring/__init__.py
fisher_scoring/fisher_scoring_focal.py
fisher_scoring/fisher_scoring_logistic.py
fisher_scoring/fisher_scoring_multinomial.py
fisher_scoring/fisher_scoring_poisson.py
fisher_scoring/fisher_scoring_robust.py
fisher_scoring/utils.py
fisher_scoring-2.0.5.post1.dist-info/licenses/LICENSE.md
fisher_scoring-2.0.5.post1.dist-info/METADATA
fisher_scoring-2.0.5.post1.dist-info/WHEEL
fisher_scoring-2.0.5.post1.dist-info/top_level.txt
fisher_scoring-2.0.5.post1.dist-info/RECORD
