Metadata-Version: 2.4
Name: fisher-scoring
Version: 2.0.5.post1
Summary: A Python implementation of the Fisher Scoring algorithm for proportion and incidence rate modeling.
Author-email: xRiskLab <contact@xrisklab.ai>
License-Expression: MIT
Project-URL: Repository, https://github.com/xRiskLab/fisher-scoring
Project-URL: Homepage, https://github.com/xRiskLab/fisher-scoring
Keywords: fisher scoring,logistic regression,maximum likelihood,classification,machine learning
Classifier: Development Status :: 4 - Beta
Classifier: Intended Audience :: Developers
Classifier: Intended Audience :: Science/Research
Classifier: Programming Language :: Python :: 3
Classifier: Programming Language :: Python :: 3.9
Classifier: Programming Language :: Python :: 3.10
Classifier: Programming Language :: Python :: 3.11
Classifier: Topic :: Scientific/Engineering :: Artificial Intelligence
Requires-Python: >=3.9
License-File: LICENSE.md
Requires-Dist: numpy<2.0.0,>=1.19.5
Requires-Dist: pandas<3.0.0,>=2.2.2
Requires-Dist: scikit-learn<2.0.0,>=1.3.0
Dynamic: license-file
